fastapi_filters_standard/__init__.py
fastapi_filters_standard/config.py
fastapi_filters_standard/configs.py
fastapi_filters_standard/docs.py
fastapi_filters_standard/fields.py
fastapi_filters_standard/filter_set.py
fastapi_filters_standard/filters.py
fastapi_filters_standard/op.py
fastapi_filters_standard/operators.py
fastapi_filters_standard/py.typed
fastapi_filters_standard/schemas.py
fastapi_filters_standard/sorters.py
fastapi_filters_standard/types.py
fastapi_filters_standard/utils.py
fastapi_filters_standard/ext/__init__.py
fastapi_filters_standard/ext/beanie.py
fastapi_filters_standard/ext/raw_sql.py
fastapi_filters_standard/ext/sqlalchemy.py
fastapi_filters_standard/ext/tortoise.py
fastapi_filters_standard-0.6.0.dist-info/METADATA
fastapi_filters_standard-0.6.0.dist-info/WHEEL
fastapi_filters_standard-0.6.0.dist-info/licenses/LICENSE
fastapi_filters_standard-0.6.0.dist-info/RECORD
