Metadata-Version: 2.4
Name: fastapi-filters-standard
Version: 0.6.0
Summary: FastAPI filters with standard query parameter syntax (comma-separated values)
Author-email: Reza Teymouri Nejad <rezatn0934@gmail.com>
License: MIT
License-File: LICENSE
Keywords: fastapi,filters,query-parameters,rest-api,sorting
Classifier: Development Status :: 4 - Beta
Classifier: Intended Audience :: Developers
Classifier: License :: OSI Approved :: MIT License
Classifier: Operating System :: OS Independent
Classifier: Programming Language :: Python :: 3
Classifier: Programming Language :: Python :: 3 :: Only
Classifier: Programming Language :: Python :: 3.10
Classifier: Programming Language :: Python :: 3.11
Classifier: Programming Language :: Python :: 3.12
Classifier: Programming Language :: Python :: 3.13
Classifier: Topic :: Internet :: WWW/HTTP :: HTTP Servers
Classifier: Topic :: Software Development :: Libraries :: Python Modules
Requires-Python: >=3.10
Requires-Dist: fastapi>=0.100.0
Requires-Dist: pydantic>=2.0.0
Requires-Dist: typing-extensions>=4.4.0
Requires-Dist: typing-inspect>=0.4.0
Provides-Extra: beanie
Requires-Dist: beanie>=1.29.0; extra == 'beanie'
Provides-Extra: raw-sql
Requires-Dist: sqlalchemy>=2.0.0; extra == 'raw-sql'
Provides-Extra: sqlalchemy
Requires-Dist: sqlalchemy>=2.0.0; extra == 'sqlalchemy'
Provides-Extra: tortoise-orm
Requires-Dist: tortoise-orm>=0.20; extra == 'tortoise-orm'
